WPE/__init__.py
WPE/db/__init__.py
WPE/db/qdrant_client_wrapper.py
WPE/db/payloads/__init__.py
WPE/db/payloads/base_payload.py
WPE/db/payloads/wpe_payload.py
WPE/db/payloads/wpe_time_based_cluster_lines_payload.py
WPE/db/payloads/wpe_time_based_cluster_payload.py
WPE/utils/__init__.py
WPE/utils/filtering.py
WPE/utils/roll_ups.py
wpe-0.0.2.dist-info/METADATA
wpe-0.0.2.dist-info/WHEEL
wpe-0.0.2.dist-info/top_level.txt
wpe-0.0.2.dist-info/RECORD
