Metadata-Version: 2.1
Name: wpe
Version: 0.0.2
Summary: A Python package for processing WPE events.
Home-page: UNKNOWN
Author: Dom and Sam
Author-email: dom@pieces.app, sam@pieces.app
License: UNKNOWN
Platform: UNKNOWN
Classifier: Programming Language :: Python :: 3
Classifier: License :: OSI Approved :: MIT License
Classifier: Operating System :: OS Independent
Requires-Python: >=3.9
Requires-Dist: langchain
Requires-Dist: langchain-community
Requires-Dist: qdrant-client
